wecom_audit/__init__.py
wecom_audit/libwecom_audit.so
wecom_audit/C_sdk/WeWorkFinanceSdk_C.h
wecom_audit/C_sdk/libWeWorkFinanceSdk_C.so
wecom_audit-0.1.6.dist-info/METADATA
wecom_audit-0.1.6.dist-info/WHEEL
wecom_audit-0.1.6.dist-info/top_level.txt
wecom_audit-0.1.6.dist-info/RECORD
