Metadata-Version: 2.4
Name: wecom-audit
Version: 0.1.6
Summary: Python wrapper for WeChat Work (WeCom) Audit API. © 2025 puyuan.tech, Ltd. All rights reserved.
Home-page: https://github.com/droomo/wecom-audit
Author: droomo, Grainstone
Author-email: th@droomo.com
Project-URL: Bug Tracker, https://github.com/droomo/wecom-audit/issues
Project-URL: Source Code, https://github.com/droomo/wecom-audit
Keywords: wecom,wechat work,audit,企业微信,企微,消息获取,会话存档,puyuan.tech
Classifier: Development Status :: 4 - Beta
Classifier: Intended Audience :: Developers
Classifier: License :: OSI Approved :: MIT License
Classifier: Programming Language :: Python :: 3
Classifier: Programming Language :: Python :: 3.11
Classifier: Operating System :: POSIX :: Linux
Classifier: Topic :: Software Development :: Libraries :: Python Modules
Requires-Python: >=3.11
Dynamic: author
Dynamic: author-email
Dynamic: classifier
Dynamic: description
Dynamic: description-content-type
Dynamic: home-page
Dynamic: keywords
Dynamic: project-url
Dynamic: requires-python
Dynamic: summary
